stopwatch/__init__.py
stopwatch/stopwatch.py
multi_task_stopwatch-0.1.0.dist-info/WHEEL
multi_task_stopwatch-0.1.0.dist-info/METADATA
multi_task_stopwatch-0.1.0.dist-info/RECORD
