Metadata-Version: 2.1
Name: multi-task-stopwatch
Version: 0.1.0
Summary: Simple stop watch, allowing for timing of a number of tasks.
Home-page: https://github.com/daya0576/simple-stopwatch
Author: changjian.zcj
Author-email: changjian.zcj@antfin.com
Requires-Python: >=3.6,<4.0
Classifier: Programming Language :: Python :: 3
Classifier: Programming Language :: Python :: 3.6
Classifier: Programming Language :: Python :: 3.7
Classifier: Programming Language :: Python :: 3.8
Classifier: Programming Language :: Python :: 3.9
Project-URL: Repository, https://github.com/daya0576/simple-stopwatch
